vecked/VERSION
vecked/__init__.py
vecked/logging.py
vecked/numbers.py
vecked/py.typed
vecked/types.py
vecked/version.py
vecked/region2/__init__.py
vecked/region2/py.typed
vecked/region2/region2f.py
vecked/vector2/__init__.py
vecked/vector2/py.typed
vecked/vector2/vector2.py
vecked/vector2/vector2f.py
vecked/vector2/vector2i.py
vecked-1.7.0.dist-info/LICENSE
vecked-1.7.0.dist-info/METADATA
vecked-1.7.0.dist-info/WHEEL
vecked-1.7.0.dist-info/top_level.txt
vecked-1.7.0.dist-info/RECORD
